Workbook

Sheet Read Me
A1: Financial Stress & Cash-Flow Risk: Management Summary
A2: Data: synthetic transactions for 120 customers, Oct 2024 to Sep 2025 (see project README).
A4: Sheet guide
A5: KPI Summary: headline numbers (all formulas, linked to the data sheets).
A6: Monthly Trend: portfolio income, expenses and savings rate by month, with charts.
A7: Category Spend: 12-month spend by category with share and rank.
A8: Band Summary: customers per stress band and per occupation (COUNTIFS / AVERAGEIFS).
A9: Customers: one row per customer with score, drivers and next-month forecast (filterable).
A10: Watch List: customers to contact first, sorted by deficit probability.
A12: Definitions
A13: Income = salary, freelance, family support, stipend and interest credits. Borrowed money is not income.
A14: Expenses = consumption + rent + EMIs + insurance + debt repayment. SIP investments are savings, not expenses.
... A21: Colour key: blue text = input data values; black text = formulas.

Sheet KPI Summary
A1: Headline KPIs (12 months, Oct 2024 to Sep 2025)
A2: KPI | B2: Value
A3: Total income | B3: ='Monthly Trend'!B14
A4: Total expenses | B4: ='Monthly Trend'!C14
A5: Net cash flow (income - expenses) | B5: ='Monthly Trend'!F14
A6: Portfolio savings rate | B6: ='Monthly Trend'!G14
A7: Total invested (SIPs) | B7: ='Monthly Trend'!D14
A8: Total borrowed (cards, loan apps, family) | B8: ='Monthly Trend'!E14
A9: Customers | B9: =COUNTA(Customers!$A$2:$A$121)
A10: Average stress score | B10: =AVERAGE(Customers!$G$2:$G$121)
A11: Customers in High or Critical stress | B11: =COUNTIF(Customers!$H:$H,"High")+COUNTIF(Customers!$H:$H,"Critical")
A12: ...as % of customers | B12: =IFERROR(B11/B9,0)
A13: Customers with < 1 month buffer | B13: =COUNTIF(Customers!$L$2:$L$121,"<1")
A14: Customers flagged High/Medium for next month | B14: =COUNTIF(Customers!$Q:$Q,"High")+COUNTIF(Customers!$Q:$Q,"Medium")
A15: Median savings rate (6m) | B15: =MEDIAN(Customers!$J$2:$J$121)
A16: Lowest-saving month | B16: =INDEX('Monthly Trend'!A2:A13,MATCH(MIN('Monthly Trend'!G2:G13),'Monthly Trend'!G2:G13,0))
A17: Highest-saving month | B17: =INDEX('Monthly Trend'!A2:A13,MATCH(MAX('Monthly Trend'!G2:G13),'Monthly Trend'!G2:G13,0))
A19: Green values link to other sheets; edit the data sheets and these update automatically.

Sheet Monthly Trend
A1: Month | B1: Income (₹) | C1: Expenses (₹) | D1: Invested (₹) | E1: Borrowed (₹) | F1: Net cash flow (₹) | G1: Savings rate | H1: Expense MoM change
A2: 2024-10 | B2: 11956637 | C2: 10033553 | D2: 600300 | E2: 28000 | F2: =B2-C2 | G2: =IFERROR(F2/B2,0)
A3: 2024-11 | B3: 11432556 | C3: 9656103 | D3: 600300 | E3: 48000 | F3: =B3-C3 | G3: =IFERROR(F3/B3,0) | H3: =IFERROR(C3/C2-1,0)
A4: 2024-12 | B4: 10632686 | C4: 9314252.4 | D4: 600300 | E4: 165000 | F4: =B4-C4 | G4: =IFERROR(F4/B4,0) | H4: =IFERROR(C4/C3-1,0)
A5: 2025-01 | B5: 10253603 | C5: 7793887.8 | D5: 600300 | E5: 142000 | F5: =B5-C5 | G5: =IFERROR(F5/B5,0) | H5: =IFERROR(C5/C4-1,0)
A6: 2025-02 | B6: 10437639 | C6: 7585065.9 | D6: 600300 | E6: 46000 | F6: =B6-C6 | G6: =IFERROR(F6/B6,0) | H6: =IFERROR(C6/C5-1,0)
A7: 2025-03 | B7: 10532694 | C7: 8546224.4 | D7: 600300 | E7: 35000 | F7: =B7-C7 | G7: =IFERROR(F7/B7,0) | H7: =IFERROR(C7/C6-1,0)
A8: 2025-04 | B8: 11250085 | C8: 9629891.4 | D8: 600300 | E8: 91000 | F8: =B8-C8 | G8: =IFERROR(F8/B8,0) | H8: =IFERROR(C8/C7-1,0)
A9: 2025-05 | B9: 10948844 | C9: 9196688.6 | D9: 595000 | E9: 97000 | F9: =B9-C9 | G9: =IFERROR(F9/B9,0) | H9: =IFERROR(C9/C8-1,0)
A10: 2025-06 | B10: 11685610 | C10: 10050623 | D10: 595000 | E10: 172000 | F10: =B10-C10 | G10: =IFERROR(F10/B10,0) | H10: =IFERROR(C10/C9-1,0)
A11: 2025-07 | B11: 10497752 | C11: 8154426.1 | D11: 586000 | E11: 70000 | F11: =B11-C11 | G11: =IFERROR(F11/B11,0) | H11: =IFERROR(C11/C10-1,0)
A12: 2025-08 | B12: 11012118 | C12: 8493857.4 | D12: 591300 | E12: 39000 | F12: =B12-C12 | G12: =IFERROR(F12/B12,0) | H12: =IFERROR(C12/C11-1,0)
A13: 2025-09 | B13: 11169300 | C13: 8249819.9 | D13: 600300 | E13: 67000 | F13: =B13-C13 | G13: =IFERROR(F13/B13,0) | H13: =IFERROR(C13/C12-1,0)
A14: Total / overall | B14: =SUM(B2:B13) | C14: =SUM(C2:C13) | D14: =SUM(D2:D13) | E14: =SUM(E2:E13) | F14: =SUM(F2:F13) | G14: =IFERROR(F14/B14,0)

Sheet Category Spend
A1: Category | B1: Spend type | C1: 12-month spend (₹) | D1: Share of spend | E1: Rank
A2: Groceries | B2: Essential Variable | C2: 23887708 | D2: =C2/SUM($C$2:$C$19) | E2: =RANK(C2,$C$2:$C$19)
A3: Housing | B3: Fixed Obligation | C3: 16124400 | D3: =C3/SUM($C$2:$C$19) | E3: =RANK(C3,$C$2:$C$19)
A4: Loan EMI | B4: Fixed Obligation | C4: 12378144 | D4: =C4/SUM($C$2:$C$19) | E4: =RANK(C4,$C$2:$C$19)
A5: Shopping | B5: Discretionary | C5: 10361358 | D5: =C5/SUM($C$2:$C$19) | E5: =RANK(C5,$C$2:$C$19)
A6: Transport | B6: Essential Variable | C6: 9048118.7 | D6: =C6/SUM($C$2:$C$19) | E6: =RANK(C6,$C$2:$C$19)
A7: Food Delivery | B7: Discretionary | C7: 7068456 | D7: =C7/SUM($C$2:$C$19) | E7: =RANK(C7,$C$2:$C$19)
A8: Education | B8: Essential Variable | C8: 4942398.4 | D8: =C8/SUM($C$2:$C$19) | E8: =RANK(C8,$C$2:$C$19)
A9: Utilities | B9: Essential Variable | C9: 4545176.7 | D9: =C9/SUM($C$2:$C$19) | E9: =RANK(C9,$C$2:$C$19)
A10: Dining Out | B10: Discretionary | C10: 3421071.6 | D10: =C10/SUM($C$2:$C$19) | E10: =RANK(C10,$C$2:$C$19)
A11: Healthcare | B11: Essential Variable | C11: 2629935.6 | D11: =C11/SUM($C$2:$C$19) | E11: =RANK(C11,$C$2:$C$19)
A12: Travel | B12: Discretionary | C12: 2353141 | D12: =C12/SUM($C$2:$C$19) | E12: =RANK(C12,$C$2:$C$19)
A13: Cash Withdrawal | B13: Discretionary | C13: 2109300 | D13: =C13/SUM($C$2:$C$19) | E13: =RANK(C13,$C$2:$C$19)
... A19: Debt Repayment | B19: Fixed Obligation | C19: 698340 | D19: =C19/SUM($C$2:$C$19) | E19: =RANK(C19,$C$2:$C$19)
A20: Total | C20: =SUM(C2:C19) | D20: =SUM(D2:D19)

Sheet Customers
A1: Customer | B1: Occupation | C1: City | D1: City tier | E1: Monthly income (₹) | F1: Active loan | G1: Stress score | H1: Stress band | I1: Top driver | J1: Savings rate (6m) | K1: Obligation ratio (6m) | L1: Buffer (months) | M1: Income CV | N1: Current balance (₹) | O1: Expected end balance (₹) | P1: P(deficit) | Q1: Forecast tier
A2: C0085 | B2: Salaried | C2: Hyderabad | D2: Tier 1 | E2: 49100 | F2: TRUE | G2: 82.5 | H2: Critical | I2: Savings margin | J2: -0.32208019 | K2: 0.8947174 | L2: 0.17476433 | M2: 0.10918001 | N2: 11097.79 | O2: -2972.66 | P2: 0.9664 | Q2: High
A3: C0019 | B3: Freelancer/Gig | C3: Patna | D3: Tier 3 | E3: 82600 | F3: FALSE | G3: 77.5 | H3: High | I3: Savings margin | J3: -0.3944389 | K3: 0.32751049 | L3: 0.21531528 | M3: 0.38491883 | N3: 14316.01 | O3: -13221.98 | P3: 0.9544 | Q3: High
A4: C0076 | B4: Salaried | C4: Indore | D4: Tier 2 | E4: 70600 | F4: TRUE | G4: 74.5 | H4: High | I4: Emergency buffer | J4: -0.08061404 | K4: 0.53172503 | L4: 0.35150252 | M4: 0.0339944 | N4: 26393.9 | O4: 24389.29 | P4: 0.3688 | Q4: Medium
A5: C0091 | B5: Salaried | C5: Ahmedabad | D5: Tier 1 | E5: 106800 | F5: TRUE | G5: 74.3 | H5: High | I5: Fixed obligations | J5: -0.099240777 | K5: 0.63982028 | L5: 0.82098903 | M5: 0.17854011 | N5: 95480.49 | O5: 100831.47 | P5: 0.0101 | Q5: Low
A6: C0059 | B6: Freelancer/Gig | C6: Pune | D6: Tier 1 | E6: 56600 | F6: FALSE | G6: 73.8 | H6: High | I6: Savings margin | J6: -0.48430818 | K6: 0.32600081 | L6: 2.4507859 | M6: 0.55783911 | N6: 97654.47 | O6: 76775.77 | P6: 0 | Q6: Low
A7: C0115 | B7: Salaried | C7: Bengaluru | D7: Tier 1 | E7: 48200 | F7: TRUE | G7: 73.6 | H7: High | I7: Savings margin | J7: -0.26816266 | K7: 0.8208582 | L7: 0.56958645 | M7: 0.098000467 | N7: 35089.3 | O7: 29868.69 | P7: 0.1612 | Q7: Low
A8: C0022 | B8: Salaried | C8: Ahmedabad | D8: Tier 1 | E8: 50200 | F8: TRUE | G8: 73.2 | H8: High | I8: Savings margin | J8: -0.11525101 | K8: 0.64693257 | L8: 0.442586 | M8: 0.024747356 | N8: 23904.95 | O8: 27121.96 | P8: 0.1592 | Q8: Low
A9: C0011 | B9: Salaried | C9: Indore | D9: Tier 2 | E9: 99000 | F9: TRUE | G9: 72.4 | H9: High | I9: Savings margin | J9: -0.32628841 | K9: 0.89405316 | L9: 0.66802293 | M9: 0.038271236 | N9: 89616.83 | O9: 61342.35 | P9: 0.1612 | Q9: Low
A10: C0103 | B10: Salaried | C10: Bengaluru | D10: Tier 1 | E10: 107500 | F10: FALSE | G10: 69.4 | H10: High | I10: Savings margin | J10: -0.18915358 | K10: 0.36546126 | L10: 3.5664463 | M10: 0.4870902 | N10: 269831.18 | O10: 262960.72 | P10: 0 | Q10: Low
A11: C0052 | B11: Student | C11: Chennai | D11: Tier 1 | E11: 16800 | F11: FALSE | G11: 65.9 | H11: High | I11: Savings margin | J11: -0.17369112 | K11: 0.50900183 | L11: 0.74786612 | M11: 0.17355508 | N11: 9459.25 | O11: 7602.65 | P11: 0.0907 | Q11: Low
A12: C0112 | B12: Salaried | C12: Indore | D12: Tier 2 | E12: 63200 | F12: FALSE | G12: 65.8 | H12: High | I12: Savings margin | J12: -0.38080142 | K12: 0.34508871 | L12: 2.3523624 | M12: 0.57543767 | N12: 72372.72 | O12: 44558.25 | P12: 0.1098 | Q12: Low
A13: C0006 | B13: Freelancer/Gig | C13: Bengaluru | D13: Tier 1 | E13: 38700 | F13: FALSE | G13: 62.4 | H13: High | I13: Savings margin | J13: -0.040705237 | K13: 0.027568063 | L13: 2.2133785 | M13: 0.48296439 | N13: 52606.19 | O13: 44209.31 | P13: 0.0057 | Q13: Low
... A121: C0120 | B121: Salaried | C121: Ahmedabad | D121: Tier 1 | E121: 129800 | F121: TRUE | G121: 0 | H121: Low | I121: None | J121: 0.41986938 | K121: 0.088870656 | L121: 21.007628 | M121: 0.034824776 | N121: 1274463.8 | O121: 1296848.5 | P121: 0 | Q121: Low

Sheet Band Summary
A1: Stress band | B1: Customers | C1: % of customers | D1: Avg score | E1: Avg savings rate | F1: Avg buffer (months) | G1: Avg obligation ratio | H1: Forecast High/Medium
A2: Low | B2: =COUNTIF(Customers!$H$2:$H$121,A2) | C2: =IFERROR(B2/$B$6,0) | D2: =IFERROR(AVERAGEIF(Customers!$H$2:$H$121,A2,Customers!$G$2:$G$121),0) | E2: =IFERROR(AVERAGEIF(Customers!$H$2:$H$121,A2,Customers!$J$2:$J$121),0) | F2: =IFERROR(AVERAGEIF(Customers!$H$2:$H$121,A2,Customers!$L$2:$L$121),0) | G2: =IFERROR(AVERAGEIF(Customers!$H$2:$H$121,A2,Customers!$K$2:$K$121),0) | H2: =COUNTIFS(Customers!$H$2:$H$121,A2,Customers!$Q$2:$Q$121,"High")+COUNTIFS(Customers!$H$2:$H$121,A2,Customers!$Q$2:$Q$121,"Medium")
A3: Moderate | B3: =COUNTIF(Customers!$H$2:$H$121,A3) | C3: =IFERROR(B3/$B$6,0) | D3: =IFERROR(AVERAGEIF(Customers!$H$2:$H$121,A3,Customers!$G$2:$G$121),0) | E3: =IFERROR(AVERAGEIF(Customers!$H$2:$H$121,A3,Customers!$J$2:$J$121),0) | F3: =IFERROR(AVERAGEIF(Customers!$H$2:$H$121,A3,Customers!$L$2:$L$121),0) | G3: =IFERROR(AVERAGEIF(Customers!$H$2:$H$121,A3,Customers!$K$2:$K$121),0) | H3: =COUNTIFS(Customers!$H$2:$H$121,A3,Customers!$Q$2:$Q$121,"High")+COUNTIFS(Customers!$H$2:$H$121,A3,Customers!$Q$2:$Q$121,"Medium")
A4: High | B4: =COUNTIF(Customers!$H$2:$H$121,A4) | C4: =IFERROR(B4/$B$6,0) | D4: =IFERROR(AVERAGEIF(Customers!$H$2:$H$121,A4,Customers!$G$2:$G$121),0) | E4: =IFERROR(AVERAGEIF(Customers!$H$2:$H$121,A4,Customers!$J$2:$J$121),0) | F4: =IFERROR(AVERAGEIF(Customers!$H$2:$H$121,A4,Customers!$L$2:$L$121),0) | G4: =IFERROR(AVERAGEIF(Customers!$H$2:$H$121,A4,Customers!$K$2:$K$121),0) | H4: =COUNTIFS(Customers!$H$2:$H$121,A4,Customers!$Q$2:$Q$121,"High")+COUNTIFS(Customers!$H$2:$H$121,A4,Customers!$Q$2:$Q$121,"Medium")
A5: Critical | B5: =COUNTIF(Customers!$H$2:$H$121,A5) | C5: =IFERROR(B5/$B$6,0) | D5: =IFERROR(AVERAGEIF(Customers!$H$2:$H$121,A5,Customers!$G$2:$G$121),0) | E5: =IFERROR(AVERAGEIF(Customers!$H$2:$H$121,A5,Customers!$J$2:$J$121),0) | F5: =IFERROR(AVERAGEIF(Customers!$H$2:$H$121,A5,Customers!$L$2:$L$121),0) | G5: =IFERROR(AVERAGEIF(Customers!$H$2:$H$121,A5,Customers!$K$2:$K$121),0) | H5: =COUNTIFS(Customers!$H$2:$H$121,A5,Customers!$Q$2:$Q$121,"High")+COUNTIFS(Customers!$H$2:$H$121,A5,Customers!$Q$2:$Q$121,"Medium")
A6: Total | B6: =SUM(B2:B5) | C6: =SUM(C2:C5) | D6: =AVERAGE(Customers!$G$2:$G$121) | H6: =SUM(H2:H5)
A9: Customers by occupation and stress band
A10: Occupation | B10: Low | C10: Moderate | D10: High | E10: Critical | F10: Total | G10: % High+Critical
A11: Salaried | B11: =COUNTIFS(Customers!$B$2:$B$121,$A11,Customers!$H$2:$H$121,B$10) | C11: =COUNTIFS(Customers!$B$2:$B$121,$A11,Customers!$H$2:$H$121,C$10) | D11: =COUNTIFS(Customers!$B$2:$B$121,$A11,Customers!$H$2:$H$121,D$10) | E11: =COUNTIFS(Customers!$B$2:$B$121,$A11,Customers!$H$2:$H$121,E$10) | F11: =SUM(B11:E11) | G11: =IFERROR((D11+E11)/F11,0)
A12: Freelancer/Gig | B12: =COUNTIFS(Customers!$B$2:$B$121,$A12,Customers!$H$2:$H$121,B$10) | C12: =COUNTIFS(Customers!$B$2:$B$121,$A12,Customers!$H$2:$H$121,C$10) | D12: =COUNTIFS(Customers!$B$2:$B$121,$A12,Customers!$H$2:$H$121,D$10) | E12: =COUNTIFS(Customers!$B$2:$B$121,$A12,Customers!$H$2:$H$121,E$10) | F12: =SUM(B12:E12) | G12: =IFERROR((D12+E12)/F12,0)
A13: Student | B13: =COUNTIFS(Customers!$B$2:$B$121,$A13,Customers!$H$2:$H$121,B$10) | C13: =COUNTIFS(Customers!$B$2:$B$121,$A13,Customers!$H$2:$H$121,C$10) | D13: =COUNTIFS(Customers!$B$2:$B$121,$A13,Customers!$H$2:$H$121,D$10) | E13: =COUNTIFS(Customers!$B$2:$B$121,$A13,Customers!$H$2:$H$121,E$10) | F13: =SUM(B13:E13) | G13: =IFERROR((D13+E13)/F13,0)

Sheet Watch List
A1: Customer | B1: Occupation | C1: City | D1: Stress score | E1: Stress band | F1: Top driver | G1: Current balance (₹) | H1: Expected end balance (₹) | I1: P(deficit) | J1: Forecast tier | K1: Suggested action
A2: C0061 | B2: Student | C2: Kolkata | D2: 57.3 | E2: Moderate | F2: Savings margin | G2: 1775.27 | H2: -4248.15 | I2: 1 | J2: High | K2: Contact this week: payment-date realignment / short-term relief
A3: C0028 | B3: Student | C3: Nagpur | D3: 53.4 | E3: Moderate | F3: Savings margin | G3: 3249.27 | H3: -1529.52 | I3: 1 | J3: High | K3: Contact this week: payment-date realignment / short-term relief
A4: C0085 | B4: Salaried | C4: Hyderabad | D4: 82.5 | E4: Critical | F4: Savings margin | G4: 11097.79 | H4: -2972.66 | I4: 0.9664 | J4: High | K4: Contact this week: payment-date realignment / short-term relief
A5: C0019 | B5: Freelancer/Gig | C5: Patna | D5: 77.5 | E5: High | F5: Savings margin | G5: 14316.01 | H5: -13221.98 | I5: 0.9544 | J5: High | K5: Contact this week: payment-date realignment / short-term relief
A6: C0094 | B6: Salaried | C6: Chennai | D6: 58.3 | E6: Moderate | F6: Fixed obligations | G6: 13085.81 | H6: 11591.53 | I6: 0.9505 | J6: High | K6: Contact this week: payment-date realignment / short-term relief
A7: C0021 | B7: Student | C7: Mumbai | D7: 53.8 | E7: Moderate | F7: Savings margin | G7: 5187.88 | H7: 1731.59 | I7: 0.8117 | J7: High | K7: Contact this week: payment-date realignment / short-term relief
A8: C0076 | B8: Salaried | C8: Indore | D8: 74.5 | E8: High | F8: Emergency buffer | G8: 26393.9 | H8: 24389.29 | I8: 0.3688 | J8: Medium | K8: Spending alert + budget plan
A9: C0079 | B9: Student | C9: Bengaluru | D9: 54.9 | E9: Moderate | F9: Savings margin | G9: 8810.55 | H9: 5606.37 | I9: 0.2258 | J9: Medium | K9: Low-balance alert
A10: C0080 | B10: Freelancer/Gig | C10: Kolkata | D10: 46.6 | E10: Moderate | F10: Emergency buffer | G10: 28476.6 | H10: 23958.28 | I10: 0.2045 | J10: Medium | K10: Low-balance alert
